<?xml version="1.0" encoding="UTF-8"?><mycoreobject xmlns:xsi="http://www.w3.org/2001/XMLSchema-instance" xmlns:xlink="http://www.w3.org/1999/xlink" ID="domlib_document_00000622" label="domlib_document_00000622" version="2.0" xsi:noNamespaceSchemaLocation="datamodel-document.xsd"><structure/><metadata xml:lang="de"><fulls class="MCRMetaBoolean" heritable="false" notinherit="false"><full xml:lang="en" inherited="0">false</full>
</fulls>
<signatures class="MCRMetaLangText" heritable="false" notinherit="false"><signature xml:lang="en" inherited="0" form="plain">DMB-007</signature>
</signatures>
<regbys class="MCRMetaLangText" heritable="false" notinherit="false"><regby xml:lang="en" inherited="0" form="plain">D.N.</regby>
</regbys>
<regdates class="MCRMetaISO8601Date" heritable="false" notinherit="false"><regdate inherited="0">2010-12-10</regdate>
</regdates>
<languages class="MCRMetaClassification" heritable="false" notinherit="false"><language inherited="0" classid="domlib_class_00000001" categid="Lan05"/>
</languages>
<wsystems class="MCRMetaClassification" heritable="false" notinherit="false"><wsystem inherited="0" classid="domlib_class_00000006" categid="WS04"/>
</wsystems>
<titles class="MCRMetaLangText" heritable="false" notinherit="false"><title xml:lang="en" inherited="0" form="plain">ʾArbaʿtu wängel “Four Gospels”</title>
</titles>
<shortcontents class="MCRMetaLangText" heritable="false" notinherit="false"><shortcontent xml:lang="en" inherited="0" form="plain">I) Introduction (fols. 3ra–10v)&#13;
- Mäqdәmä wängel “Introduction to the Gospel” (fols. 3ra – 7va)&#13;
- Statement about the Eusebian sections (fol. 7va)&#13;
- Canon Tables (fols. 7va-10r)&#13;
II) Gospel of Matthew (fols. 11ra–52rb)&#13;
- Bәsratä Matewos “Gospel of Matthew” (fols. 11ra–52ra)&#13;
- Postscript (fols. 52ra– 52rb)&#13;
III) Gospel of Mark (fols. 52rb–77va)&#13;
- Biography of Mark (fols. 52rb–52va)&#13;
- List of the “tituli” for the Gospel of Mark: 26 titles (fols. 52va–52vb)&#13;
- Bәsratä Marqos “Gospel of Mark” (fols. 53ra–77va)&#13;
- Postscript  (fol. 77va)&#13;
IV) Gospel of Luke (fols. 78ra–112vb)&#13;
- Bәsratä Luqas “Gospel of Luke” (fols. 78ra–112vb)&#13;
- Postscript (fol. 112vb)&#13;
V) Gospel of John (fols. 112vb–147va)&#13;
- Biography of John (fols. 112vb–113rb)&#13;
- List of the “tituli” for the Gospel of John: 21 titles (fol. 113va)&#13;
- Bәsratä Yoḥannәs “Gospel of John” (fols. 114ra–146rb)&#13;
- Postscript (fols. 146rb–147va)&#13;
&#13;
Additiones 1-6.</shortcontent>
</shortcontents>
<subjects class="MCRMetaClassification" heritable="false" notinherit="false"><subject inherited="0" classid="domlib_class_00000002" categid="Sub02.2"/>
</subjects>
<originlinks class="MCRMetaLinkID" heritable="false" notinherit="false"><originlink inherited="0" xlink:type="locator" xlink:href="domlib_institution_00000131" xlink:title="Bäʿatti Qәddus Mikaʾel  / DMB"/>
</originlinks>
<locationlinks class="MCRMetaLinkID" heritable="false" notinherit="false"><locationlink inherited="0" xlink:type="locator" xlink:href="domlib_institution_00000131" xlink:title="Bäʿatti Qәddus Mikaʾel  / DMB"/>
</locationlinks>
<donors class="MCRMetaLangText" heritable="false" notinherit="false"><donor xml:lang="en" inherited="0" form="plain">Gäbrä ʾƎgziʾabǝḥer, according to Additione 1 and 2.&#13;
Besides, Additio 1 and 2 mentions names of other individuals (probably his relatives): Wäldä Sǝmʿon, Wälättä Mikaʾel, ʿAmdä Mikaʾel, Mäzgäbä Śǝllase, Wälda Yoḥannǝs, Täklä Haymanot, Wälättä Yoḥannǝs, Wälättä Giyorgis, ʾAmätä ʾIyäsus, Wälättä ʾAbiyä ʾƎgziʾ, Wälättä ʾAbiyä ʾƎgziʾ, Wälättä Ṣadǝqan, Wälättä Mädḫǝn.&#13;
Some of these names are also mentioned in the supplication formulas, at the end of several sub-sections (s., e.g., fols. 7va, 16va), added in a different hand.</donor>
</donors>
<fdatings class="MCRMetaISO8601Date" heritable="false" notinherit="false"><fdating inherited="0">1889</fdating>
</fdatings>
<tdatings class="MCRMetaISO8601Date" heritable="false" notinherit="false"><tdating inherited="0">1913</tdating>
</tdatings>
<dcomments class="MCRMetaLangText" heritable="false" notinherit="false"><dcomment xml:lang="en" inherited="0" form="plain">Additio 1 mentions King Mǝnilǝk (r. 1889-1913) and Metropolitan Ṗeṭros (in tenure 1881-1917).&#13;
Additio 1 refers to the year of Mark the Evangelist. This means that the Ms. could have been written in years 1889/90, 1897/98, 1905/6 or 1912/13(cp. ChChron 219).</dcomment>
</dcomments>
<catstates class="MCRMetaClassification" heritable="false" notinherit="false"><catstate inherited="0" classid="domlib_class_00000005" categid="St01"/>
</catstates>
<cbadditions class="MCRMetaBoolean" heritable="false" notinherit="false"><cbaddition xml:lang="en" inherited="0">true</cbaddition>
</cbadditions>
<restorations class="MCRMetaClassification" heritable="false" notinherit="false"><restoration inherited="0" classid="domlib_class_00000007" categid="Res03"/>
</restorations>
<mslits class="MCRMetaLangText" heritable="false" notinherit="false"><mslit xml:lang="en" inherited="0" form="plain">Ms. previously unknown.</mslit>
</mslits>
<nmtexts class="MCRMetaNumber" heritable="false" notinherit="false"><nmtext xml:lang="en" inherited="0">5.0</nmtext>
</nmtexts>
<nmunits class="MCRMetaNumber" heritable="false" notinherit="false"><nmunit xml:lang="en" inherited="0">1.0</nmunit>
</nmunits>
<mwidths class="MCRMetaNumber" heritable="false" notinherit="false"><mwidth xml:lang="en" inherited="0">21.0</mwidth>
</mwidths>
<mheights class="MCRMetaNumber" heritable="false" notinherit="false"><mheight xml:lang="en" inherited="0">26.0</mheight>
</mheights>
<mthicknesses class="MCRMetaNumber" heritable="false" notinherit="false"><mthickness xml:lang="en" inherited="0">6.5</mthickness>
</mthicknesses>
<mratios class="MCRMetaNumber" heritable="false" notinherit="false"><mratio xml:lang="en" inherited="0">0.8077</mratio>
</mratios>
<bindings class="MCRMetaLangText" heritable="false" notinherit="false"><binding xml:lang="en" inherited="0" form="plain">Wooden boards covered with reddish brown tooled leather.&#13;
Two pairs of sewing stations.</binding>
</bindings>
<bnendbands class="MCRMetaBoolean" heritable="false" notinherit="false"><bnendband xml:lang="en" inherited="0">true</bnendband>
</bnendbands>
<bnmaterials class="MCRMetaClassification" heritable="false" notinherit="false"><bnmaterial inherited="0" classid="domlib_class_00000003" categid="BMat02"/>
<bnmaterial inherited="0" classid="domlib_class_00000003" categid="BMat05"/>
</bnmaterials>
<bnoriginals class="MCRMetaClassification" heritable="false" notinherit="false"><bnoriginal inherited="0" classid="domlib_class_00000008" categid="OB03"/>
</bnoriginals>
<bnothers class="MCRMetaLangText" heritable="false" notinherit="false"><bnother xml:lang="en" inherited="0" form="plain">Two pairs of chains of endband stitches at the spine cover.</bnother>
</bnothers>
<wmaterials class="MCRMetaClassification" heritable="false" notinherit="false"><wmaterial inherited="0" classid="domlib_class_00000004" categid="WMat01"/>
</wmaterials>
<inks class="MCRMetaLangText" heritable="false" notinherit="false"><ink xml:lang="en" inherited="0" form="plain">Black; red.</ink>
</inks>
<folios class="MCRMetaNumber" heritable="false" notinherit="false"><folio xml:lang="en" inherited="0">147.0</folio>
</folios>
<blankfolios class="MCRMetaNumber" heritable="false" notinherit="false"><blankfolio xml:lang="en" inherited="0">3.0</blankfolio>
</blankfolios>
<txbfolios class="MCRMetaLangText" heritable="false" notinherit="false"><txbfolio xml:lang="en" inherited="0" form="plain">fols. 1rv, 2rv, 147v</txbfolio>
</txbfolios>
<quires class="MCRMetaNumber" heritable="false" notinherit="false"><quire xml:lang="en" inherited="0">22.0</quire>
</quires>
<txquires class="MCRMetaLangText" heritable="false" notinherit="false"><txquire xml:lang="en" inherited="0" form="plain">A + 21</txquire>
</txquires>
<squires class="MCRMetaLangText" heritable="false" notinherit="false"><squire xml:lang="en" inherited="0" form="plain">A (2/fols. 1r-2v)-I(4/fols. 3r-6v)-II(4/fols. 7r-10v)-III(8/fols. 11r-18v)-IV(8/fols. 19r-26v)-V(6/fols. 27r-32v)-VI(6/fols. 33r-38v)-VII(6/fols. 39r-44v)-VIII(8/fols. 45r-52v)-IX(8/fols. 53r-60v)-X(8/fols. 61r-68v)-XI(9; s.l.: 9, stub before 2/fols. 69r-77v)-XII(8/fols. 78r-85v)-XIII(8/fols. 86r-93v)-XIV(6/fols. 94r-99v)-XV(8/fols. 100r-107v)-XVI(6/fols. 108r-113v)-XVII(8/fols. 114r-121v)-XVIII(8/fols. 122r-129v)-XIX(8/fols. 130r-137v)-XX(8/fols. 138r–145v)-XXI(2/fols. 146r-147v).</squire>
</squires>
<taunits class="DLTextArea" heritable="false" notinherit="false"><taunit xml:lang="en" inherited="0"><ta-width>17.5</ta-width><ta-height>20.5</ta-height><ta-col2>1.4</ta-col2><ta-ratio>0.8537</ta-ratio><mr-top>2.2</mr-top><mr-left>1.1</mr-left><mr-col2>1.4</mr-col2><mr-right>2.4</mr-right><mr-bottom>3.3</mr-bottom><mr-info>All data for fol. 5r.</mr-info><cl-nm>2</cl-nm><ln-nm>25</ln-nm><ln-info>25/28</ln-info><rl-info>Pricking and ruling are visible; &#13;
Ruling pattern: &#13;
1A-1A-1A1A/0-0/0-0/C; &#13;
Primary pricks are visible; &#13;
Ruling pricks are visible; &#13;
The upper line is written above the ruling; &#13;
The bottom line is written above the ruling.</rl-info></taunit>
</taunits>
<ptypeofscripts class="MCRMetaLangText" heritable="false" notinherit="false"><ptypeofscript xml:lang="en" inherited="0" form="plain">Late 19th - early 20th century</ptypeofscript>
</ptypeofscripts>
<phandwritings class="MCRMetaLangText" heritable="false" notinherit="false"><phandwriting xml:lang="en" inherited="0" form="plain">Mediocre</phandwriting>
</phandwritings>
<rubrications class="MCRMetaLangText" heritable="false" notinherit="false"><rubrication xml:lang="en" inherited="0" form="plain">Nomina sacra; the word mәʿәraf (“chapter”) and the chapter numbers; two lines on the incipit page (fol. 3r) of the Introduction; some lines on the incipit page of each Gospel, divided into several groups, alternating with black lines: 6 lines for the Gospels of Matthew and John, 4 lines for the Gospel of Luke and 7 lines for the Gospel of Mark; 1-3 lines in the incipit of all the chapters; some paragraph beginnings (1-3 lines) and some other passages; incipit (one line) of some minor texts within the Introduction and the Postscript;&#13;
parts of the Canon tables; Ethiopic numerals indicating the “tituli”; elements of the punctuation signs.</rubrication>
</rubrications>
<abbreviations class="MCRMetaLangText" heritable="false" notinherit="false"><abbreviation xml:lang="en" inherited="0" form="plain">ማርያ፡ for ማርያም፡ (esp. fol. 11va [l.19]) &#13;
ምዕ፡ for ምዕራፍ፡ (e.g.: fols. 14va [l.22], 71va [l.9])&#13;
ም፡ for ምዕራፍ፡ (e.g.: fols. 19va [l.3], 58rb [l.3])</abbreviation>
</abbreviations>
<otherdetails class="MCRMetaLangText" heritable="false" notinherit="false"><otherdetail xml:lang="en" inherited="0" form="plain">Concerning the introduction, the contents and the postscript of the Gospels, cp. R. ZUURMOND, Novum Testamentum Aethiopice: the Synoptic Gospels, Part I: General Introduction, Part II: Edition of the Gospel of Mark, Stuttgart 1989 (AeF 27), 1-31.&#13;
The lists of the “Tituli” for the Gospels of Matthew and Luke are missing.&#13;
The Gospels of Mark, Luke and John are introduced by “Opening Lines” which include a blessing (s. in fols. 53rab, 78rab, 114ra [ls. 1-6]). In the Gospels of Mark and of Luke these lines are separated from the main text by a sequence of nine dot asterisks.&#13;
Concerning the “Opening Lines”, cp. R. ZUURMOND, Novum Testamentum Aethiopice: the Synoptic Gospels, Part I: General Introduction, (AeF 27), 23-24.&#13;
The postscripts for all the Gospels include a note on their date of origin.</otherdetail>
</otherdetails>
<desccontents class="DLMetaContent" heritable="false" notinherit="false"><desccontent xml:lang="en" inherited="0"><editions class="DLBibliography"><edition xml:lang="en" inherited="0"><isLink>no</isLink></edition></editions><literatures class="DLBibliography"><literature xml:lang="en" inherited="0"><isLink>no</isLink></literature></literatures></desccontent>
</desccontents>
<additionals class="DLAdditional" heritable="false" notinherit="false"><additional xml:lang="en" inherited="0"><cont>&lt;p&gt;&lt;span style="font-size: small;"&gt;&lt;span lang="EN-US" arial="" sans-serif=""&gt;Fol. 2r: Donation note.&lt;/span&gt;&lt;/span&gt;&lt;/p&gt;</cont><add>&lt;p&gt;&lt;span lang="EN-US" sans-serif="" arial="" style="line-height: 115%; font-size: 10pt;"&gt;Fol. 2r: &lt;/span&gt;&lt;span lang="EN-US" style="line-height: 115%; font-family: Nyala; font-size: 12pt;"&gt;&amp;#4829;&amp;#4632;&amp;#4925;&amp;#4624;&amp;#4941;&amp;#4961; &amp;#4824;&amp;#4872;&amp;#4709;&amp;#4648;&amp;#4961; &amp;#4773;&amp;#4877;&amp;#4826;&amp;#4768;&amp;#4709;&amp;#4628;&amp;#4653;&amp;#4961; &amp;#4824;&amp;#4808;&amp;#4624;&amp;#4710;&amp;#4961; &amp;#4616;&amp;#4723;&amp;#4710;&amp;#4720;&amp;#4961; &amp;#4634;&amp;#4779;&amp;#4772;&amp;#4621;&amp;#4961; &amp;#4704;&amp;#4768;&amp;#4722;&amp;#4961; &amp;#4776;&amp;#4632;&amp;#4961; &amp;#4845;&amp;#4777;&amp;#4758;&amp;#4961; &amp;#4632;&amp;#4853;&amp;#4739;&amp;#4720;&lt;/span&gt;&lt;span lang="EN-US" sans-serif="" arial="" style="line-height: 115%; font-size: 10pt;"&gt;[sic]&lt;/span&gt;&lt;span lang="EN-US" style="line-height: 115%; font-family: Nyala; font-size: 12pt;"&gt;&amp;#4961; &amp;#4752;&amp;#4941;&amp;#4661;&amp;#4961; &amp;#4808;&amp;#4645;&amp;#4875;&amp;#4961; &amp;#4637;&amp;#4661;&amp;#4616;&amp;#4961; &amp;#4768;&amp;#4705;&amp;#4609;&amp;#4961; &amp;#4808;&amp;#4621;&amp;#4848;&amp;#4961; &amp;#4661;&amp;#4637;&amp;#4822;&amp;#4757;&amp;#4961; &amp;#4808;&amp;#4709;&amp;#4773;&amp;#4658;&amp;#4721;&amp;#4961; &amp;#4808;&amp;#4616;&amp;#4720;&amp;#4961; &amp;#4634;&amp;#4779;&amp;#4772;&amp;#4621;&amp;#4961; &amp;#4808;&amp;#4768;&amp;#4705;&amp;#4611;&amp;#4961; &amp;#4768;&amp;#4637;&amp;#4848;&amp;#4961; &amp;#4634;&amp;#4779;&amp;#4772;&amp;#4621;&amp;#4961; &amp;#4808;&amp;#4617;&amp;#4849;&lt;/span&gt;&lt;span lang="EN-US" sans-serif="" arial="" style="line-height: 115%; font-size: 10pt;"&gt;[sic]&lt;/span&gt;&lt;span lang="EN-US" style="line-height: 115%; font-family: Nyala; font-size: 12pt;"&gt;&amp;#4961; &amp;#4632;&amp;#4829;&amp;#4872;&amp;#4704;&amp;#4961; &amp;#4645;&amp;#4619;&amp;#4660;&amp;#4961; &amp;#4808;&amp;#4621;&amp;#4848;&amp;#4961; &amp;#4846;&amp;#4624;&amp;#4757;&amp;#4661;&amp;#4961; &amp;#4808;&amp;#4720;&amp;#4781;&amp;#4616;&amp;#4961; &amp;#4611;&amp;#4845;&amp;#4635;&amp;#4758;&amp;#4725;&amp;#4961; &amp;#4808;&amp;#4616;&amp;#4720;&amp;#4961; &amp;#4846;&amp;#4624;&amp;#4757;&amp;#4661;&amp;#4961; &amp;#4808;&amp;#4616;&amp;#4720;&amp;#4961; &amp;#4874;&amp;#4846;&amp;#4653;&amp;#4874;&amp;#4661;&amp;#4961; &amp;#4768;&amp;#4632;&amp;#4720;&amp;#4961; &amp;#4770;&amp;#4840;&amp;#4657;&amp;#4661;&amp;#4961; &amp;#4808;&amp;#4616;&amp;#4720;&amp;#4961; &amp;#4768;&amp;#4706;&amp;#4840;&amp;#4961; &amp;#4773;&amp;#4877;&amp;#4826;&amp;#4773;&amp;#4961; &amp;#4808;&amp;#4624;&amp;#4635;&amp;#4721;&amp;#4961; &amp;#4808;&amp;#4616;&amp;#4720;&amp;#4961; &amp;#4768;&amp;#4706;&amp;#4840;&amp;#4961; &amp;#4773;&amp;#4877;&amp;#4826;&amp;#4773;&amp;#4961; &amp;#4808;&amp;#4773;&amp;#4741;&amp;#4721;&amp;#4961; &amp;#4808;&amp;#4616;&amp;#4720;&amp;#4961; &amp;#4923;&amp;#4853;&amp;#4675;&amp;#4757;&amp;#4961; &amp;#4808;&amp;#4616;&amp;#4720;&amp;#4961; &amp;#4632;&amp;#4853;&amp;#4741;&amp;#4757;&amp;#4961; &amp;#4824;&amp;#4656;&amp;#4648;&amp;#4678;&amp;#4961; &amp;#4808;&amp;#4824;&amp;#4936;&amp;#4624;&amp;#4678;&amp;#4961; &amp;#4813;&amp;#4873;&amp;#4824;&amp;#4961; &amp;#4616;&amp;#4845;&amp;#4777;&amp;#4757;&amp;#4961; &amp;#4704;&amp;#4661;&amp;#4621;&amp;#4899;&amp;#4752;&amp;#4961; &amp;#4916;&amp;#4901;&amp;#4654;&amp;#4661;&amp;#4961; &amp;#4808;&amp;#4915;&amp;#4622;&amp;#4661;&lt;/span&gt;&lt;span lang="EN-US" sans-serif="" arial="" style="line-height: 115%; font-size: 10pt;"&gt;[sic]&lt;/span&gt;&lt;span lang="EN-US" style="line-height: 115%; font-family: Nyala; font-size: 12pt;"&gt;&amp;#4961; &amp;#4704;&amp;#4768;&amp;#4936;&amp;#4961; &amp;#4768;&amp;#4709;&amp;#4961; &amp;#4808;&amp;#4621;&amp;#4853;&amp;#4961; &amp;#4808;&amp;#4632;&amp;#4757;&amp;#4936;&amp;#4661;&amp;#4961; &amp;#4677;&amp;#4849;&amp;#4661;&amp;#4961; &amp;#4770;&amp;#4725;&amp;#4653;&amp;#4661;&amp;#4817;&amp;#4754;&amp;#4961; &amp;#4768;&amp;#4704;&amp;#4813;&amp;#4840;&amp;#4961; &amp;#4808;&amp;#4768;&amp;#4739;&amp;#4813;&amp;#4840;&amp;#4961; &amp;#4779;&amp;#4613;&amp;#4755;&amp;#4725;&amp;#4961; &amp;#4808;&amp;#4850;&amp;#4843;&amp;#4678;&amp;#4755;&amp;#4725;&amp;#4961; &amp;#4720;&amp;#4925;&amp;#4629;&amp;#4936;&amp;#4961; &amp;#4808;&amp;#4720;&amp;#4872;&amp;#4827;&amp;#4961; &amp;#4808;&amp;#4704;&amp;#4632;&amp;#4752;&lt;/span&gt;&lt;span lang="EN-US" sans-serif="" arial="" style="line-height: 115%; font-size: 10pt;"&gt;[sic]&lt;/span&gt;&lt;span lang="EN-US" style="line-height: 115%; font-family: Nyala; font-size: 12pt;"&gt;&amp;#4961; &amp;#4635;&amp;#4653;&amp;#4678;&amp;#4661;&amp;#4961; &amp;#4808;&amp;#4757;&amp;#4876;&amp;#4619;&amp;#4810;&amp;#4961; &amp;#4808;&amp;#4757;&amp;#4873;&amp;#4645;&amp;#4752;&amp;#4961; &amp;#4637;&amp;#4757;&amp;#4621;&amp;#4781;&lt;/span&gt;&lt;span lang="EN-US" style="line-height: 115%; font-family: Nyala; font-size: 12pt;"&gt;&amp;#4961; &amp;#4808;&amp;#4915;&amp;#4915;&amp;#4661;&amp;#4752;&amp;#4961; &amp;#4916;&amp;#4901;&amp;#4654;&amp;#4661;&amp;#4961; &amp;#4704;&amp;#4768;&amp;#4853;&amp;#4961; &amp;#4877;&amp;#4651;&amp;#4725;&amp;#4961; &amp;#4872;&amp;#4704;&amp;#4843;&amp;#4961;&lt;span&gt;&amp;#160; &lt;/span&gt;&amp;#4851;&amp;#4763;&amp;#4610;&amp;#4961; &amp;#4632;&amp;#4637;&amp;#4613;&amp;#4653;&amp;#4961; &amp;#4720;&amp;#4781;&amp;#4616;&amp;#4961; &amp;#4624;&amp;#4845;&amp;#4635;&amp;#4758;&amp;#4725;&amp;#4961; &amp;#4616;&amp;#4819;&amp;#4616;&amp;#4632;&amp;#4961; &amp;#4768;&amp;#4616;&amp;#4637;&amp;#4961; &amp;#4768;&amp;#4636;&amp;#4757;&amp;#4961; &amp;#4808;&amp;#4768;&amp;#4637;&amp;#4840;&amp;#4757;&lt;/span&gt;&lt;span lang="EN-US" sans-serif="" arial="" style="line-height: 115%; font-size: 10pt;"&gt;[sic]&lt;/span&gt;&lt;span lang="EN-US" style="line-height: 115%; font-family: Nyala; font-size: 12pt;"&gt;&amp;#4961; &amp;#4616;&amp;#4845;&amp;#4757;&amp;#4961; &amp;#4616;&amp;#4845;&amp;#4757;&amp;#4961;&lt;/span&gt;&lt;/p&gt;</add><tran>&lt;p class="MsoNormal" style="text-align: left; line-height: normal; margin-bottom: 0pt;"&gt;&lt;span style="font-size: small;"&gt;&lt;span lang="EN-US" sans-serif="" arial=""&gt;Fol. 2r: This is the book of G&amp;#228;br&amp;#228; &amp;#704;&lt;/span&gt;&lt;span lang="EN-US" sans-serif="" arial=""&gt;&amp;#398;&lt;/span&gt;&lt;span lang="EN-US" sans-serif="" arial=""&gt;gzi&amp;#704;ab&amp;#477;&amp;#7717;er which he donated to the tabot of (the church of) Mika&amp;#704;el B&amp;#228;&amp;#704;atti, so that it might be for him the salvation of the soul and the body, together with his father W&amp;#228;ld&amp;#228; S&lt;/span&gt;&lt;span lang="EN-US" sans-serif="" arial=""&gt;&amp;#601;&lt;/span&gt;&lt;span lang="EN-US" sans-serif="" arial=""&gt;m&lt;/span&gt;&lt;span lang="EN-US" sans-serif="" arial=""&gt;&amp;#601;&lt;/span&gt;&lt;span lang="EN-US" sans-serif="" arial=""&gt;&amp;#705;on and his wife W&amp;#228;l&amp;#228;tt&amp;#228; Mika&amp;#704;el and her father &amp;#705;Amd&amp;#228; Mika&amp;#704;el, his children M&amp;#228;zg&amp;#228;b&amp;#228; &amp;#346;&lt;/span&gt;&lt;span lang="EN-US" sans-serif="" arial=""&gt;&amp;#601;&lt;/span&gt;&lt;span lang="EN-US" sans-serif="" arial=""&gt;llase, W&amp;#228;lda Yo&amp;#7717;ann&lt;/span&gt;&lt;span lang="EN-US" sans-serif="" arial=""&gt;&amp;#601;&lt;/span&gt;&lt;span lang="EN-US" sans-serif="" arial=""&gt;s and T&amp;#228;kl&amp;#228; Haymanot, W&amp;#228;l&amp;#228;tt&amp;#228; Yo&amp;#7717;ann&lt;/span&gt;&lt;span lang="EN-US" sans-serif="" arial=""&gt;&amp;#601;&lt;/span&gt;&lt;span lang="EN-US" sans-serif="" arial=""&gt;s, W&amp;#228;l&amp;#228;tt&amp;#228; Giyorgis, &amp;#704;Am&amp;#228;t&amp;#228; &amp;#704;Iy&amp;#228;sus, W&amp;#228;l&amp;#228;tt&amp;#228; &amp;#704;Abiy&amp;#228; &amp;#704;&lt;/span&gt;&lt;span lang="EN-US" sans-serif="" arial=""&gt;&amp;#398;&lt;/span&gt;&lt;span lang="EN-US" sans-serif="" arial=""&gt;gzi&amp;#704; and&amp;#160; his mother-in law W&amp;#228;l&amp;#228;tt&amp;#228; &amp;#704;Abiy&amp;#228; &amp;#704;&lt;/span&gt;&lt;span lang="EN-US" sans-serif="" arial=""&gt;&amp;#398;&lt;/span&gt;&lt;span lang="EN-US" sans-serif="" arial=""&gt;gzi&amp;#704;, and his sisters W&amp;#228;l&amp;#228;tt&amp;#228; &amp;#7778;ad&lt;/span&gt;&lt;span lang="EN-US" sans-serif="" arial=""&gt;&amp;#601;&lt;/span&gt;&lt;span lang="EN-US" sans-serif="" arial=""&gt;qan, W&amp;#228;l&amp;#228;tt&amp;#228; M&amp;#228;d&amp;#7723;&lt;/span&gt;&lt;span lang="EN-US" sans-serif="" arial=""&gt;&amp;#601;&lt;/span&gt;&lt;span lang="EN-US" sans-serif="" arial=""&gt;n.&lt;/span&gt; &lt;span lang="EN-US" sans-serif="" arial=""&gt;May the one who stole it (the book) and erased it be excommunicated by&lt;/span&gt;&lt;span lang="EN-US" sans-serif="" arial=""&gt; the power of Peter and Paul, through the mouth of the Father, Son and Holy Spirit. May you, my fathers and my brothers, priests and deacons&lt;i&gt;, &lt;/i&gt;not forget (to pray) for my sake! &lt;/span&gt;&lt;/span&gt;&lt;/p&gt;&#13;
&lt;p class="MsoNormal" style="text-align: left; line-height: normal; margin-bottom: 0pt;"&gt;&lt;span style="font-size: small;"&gt;&lt;span lang="EN-US" sans-serif="" arial="" style="line-height: 115%;"&gt;(The book) was written and bought in the year of the Evangelist Mark and the king M&lt;/span&gt;&lt;span lang="EN-US" sans-serif="" arial="" style="line-height: 115%;"&gt;&amp;#601;&lt;/span&gt;&lt;span lang="EN-US" sans-serif="" arial="" style="line-height: 115%;"&gt;n&lt;/span&gt;&lt;span lang="EN-US" sans-serif="" arial="" style="line-height: 115%;"&gt;i&lt;/span&gt;&lt;span lang="EN-US" sans-serif="" arial="" style="line-height: 115%;"&gt;l&lt;/span&gt;&lt;span lang="EN-US" sans-serif="" arial="" style="line-height: 115%;"&gt;&amp;#601;&lt;/span&gt;&lt;span lang="EN-US" sans-serif="" arial="" style="line-height: 115%;"&gt;k and our metropolitan &amp;#7766;e&amp;#7789;ros,&amp;#160;at the market in &amp;#705;Addigrat; the judge (was) m&amp;#228;mh&amp;#1241;r T&amp;#228;kl&amp;#228; &amp;#7716;aymanot. Forever and ever. Amen and Amen. So be&amp;#160; it, so be it.&amp;#160; &lt;/span&gt;&lt;/span&gt;&lt;/p&gt;&#13;
&lt;p&gt;&lt;/p&gt;</tran></additional>
<additional xml:lang="en" inherited="0"><cont>&lt;p&gt;&lt;span lang="EN-US" sans-serif="" arial="" style="font-size: 10pt;"&gt;Fol. 52vb: Donation note.&lt;/span&gt;&lt;/p&gt;</cont><det>The note is an abridged version of the note in fol. 2r: it states that the manuscript was initially property of Gäbrä ʾƎgziʾabǝḥer who donated it to the tabot of the church of Mikaʾel Bäʾatti. It repeats the same names of the relatives of the donor.</det></additional>
<additional xml:lang="en" inherited="0"><cont>&lt;p style="text-align: left; line-height: normal; margin-bottom: 0pt;" class="MsoNormal"&gt;&lt;span style="font-size: small;"&gt;&lt;span lang="EN-US" arial="" sans-serif=""&gt;Fol. 77va-vb: Record concerning reconciliation between &amp;#7689;&lt;/span&gt;&lt;span lang="EN-US" arial="" sans-serif=""&gt;&amp;#601;&lt;/span&gt;&lt;span lang="EN-US" arial="" sans-serif=""&gt;qa (&lt;/span&gt;&lt;span lang="EN-US" arial="" sans-serif=""&gt;&amp;#353;&lt;/span&gt;&lt;span lang="EN-US" arial="" sans-serif=""&gt;ums) and the community of B&amp;#228;&amp;#704;atti.&lt;/span&gt;&lt;/span&gt;&lt;/p&gt;</cont><det>The note mentions the date 1922 E.C. (= 1929/30 A.D.).</det></additional>
<additional xml:lang="en" inherited="0"><cont>&lt;p&gt;&lt;span style="font-size: small;"&gt;&lt;span lang="EN-US" sans-serif="" arial=""&gt;Fol. 113va-vb: Record&lt;/span&gt;&lt;span lang="EN-US" sans-serif="" arial=""&gt; concerning heritage (?).&lt;/span&gt;&lt;/span&gt;&lt;/p&gt;</cont><det>The note mentions the date 1951 E.C. (1958/59 A.D.), 8th of Mäskäräm.</det></additional>
<additional xml:lang="en" inherited="0"><cont>&lt;p&gt;&lt;span style="font-size: small;"&gt;&lt;span lang="EN-US" sans-serif="" arial=""&gt;Fol. 146va-vb: Record concerning the purchase of a house. &lt;/span&gt;&lt;/span&gt;&lt;/p&gt;</cont><det>The note mentions the date 1914 E.C. (= 1921/22 A.D.).</det></additional>
<additional xml:lang="en" inherited="0"><cont>&lt;p&gt;&lt;span style="font-size: small;"&gt;&lt;span lang="EN-US"&gt;Fol. 147r: Record concerning the purchase of a house.&lt;/span&gt;&lt;/span&gt;&lt;/p&gt;</cont><det>The note mentions the date 1922 E.C. (1929/30 A.D.), 16th Mäggabit.</det></additional>
</additionals>
<extras class="MCRMetaLangText" heritable="false" notinherit="false"><extra xml:lang="en" inherited="0" form="plain">- Fol. 147r: Crude recent notes (below the text of Additio VI).&#13;
- Fol. 10v: Crude drawings in pencil.&#13;
- Crude notes in pencil or in pen in the upper margin: fols. 6r, 17r, 17v, 20v, 22r, 25r, 27r, 29r, 34r, 36r, 46r, 57r, 61v, 65r, 68v, 98v, 119r, 140r, 144r.</extra>
</extras>
<frames class="MCRMetaLangText" heritable="false" notinherit="false"><frame xml:lang="en" inherited="0" form="plain">- Fol. 11r: simple, narrow, uncoloured horizontal ornamental band at the top of the incipit page of Text II. Geometric motifs.</frame>
</frames>
</metadata><service><servdates class="MCRMetaISO8601Date"><servdate inherited="0" type="createdate">2011-10-25T10:16:38.286Z</servdate><servdate inherited="0" type="modifydate">2015-05-04T07:53:08.205Z</servdate></servdates><servflags class="MCRMetaLangText"><servflag xml:lang="en" inherited="0" form="plain" type="creator">VPisani</servflag><servflag xml:lang="en" inherited="0" form="plain" type="editor">MVilla</servflag></servflags><servacls class="MCRMetaAccessRule"><servacl permission="deletedb"><condition format="xml"><boolean operator="and"><boolean operator="or"><condition field="group" operator="=" value="admingroup"/><condition field="group" operator="=" value="ethioadmins"/></boolean><boolean operator="true"/><boolean operator="true"/></boolean></condition></servacl><servacl permission="read"><condition format="xml"><boolean operator="true"/></condition></servacl><servacl permission="writedb"><condition format="xml"><boolean operator="and"><boolean operator="or"><condition field="group" operator="=" value="admingroup"/><condition field="group" operator="=" value="ethioleaders"/></boolean><boolean operator="true"/><boolean operator="true"/></boolean></condition></servacl></servacls></service></mycoreobject>