<?xml version="1.0" encoding="UTF-8"?><mycoreobject xmlns:xsi="http://www.w3.org/2001/XMLSchema-instance" xmlns:xlink="http://www.w3.org/1999/xlink" ID="domlib_document_00002856" label="domlib_document_00002856" version="2.0" xsi:noNamespaceSchemaLocation="datamodel-document.xsd"><structure/><metadata xml:lang="de"><fulls class="MCRMetaBoolean" heritable="false" notinherit="false"><full xml:lang="en" inherited="0">false</full>
</fulls>
<signatures class="MCRMetaLangText" heritable="false" notinherit="false"><signature xml:lang="en" inherited="0" form="plain">UM-030</signature>
</signatures>
<regbys class="MCRMetaLangText" heritable="false" notinherit="false"><regby xml:lang="en" inherited="0" form="plain">D.N.</regby>
</regbys>
<regdates class="MCRMetaISO8601Date" heritable="false" notinherit="false"><regdate inherited="0">2011-11-23</regdate>
</regdates>
<languages class="MCRMetaClassification" heritable="false" notinherit="false"><language inherited="0" classid="domlib_class_00000001" categid="Lan05"/>
</languages>
<wsystems class="MCRMetaClassification" heritable="false" notinherit="false"><wsystem inherited="0" classid="domlib_class_00000006" categid="WS04"/>
</wsystems>
<titles class="MCRMetaLangText" heritable="false" notinherit="false"><title xml:lang="en" inherited="0" form="plain">Fragments</title>
</titles>
<shortcontents class="MCRMetaLangText" heritable="false" notinherit="false"><shortcontent xml:lang="en" inherited="0" form="plain">UM-30 ff. 3rv: 1 Sam 24:15-25:14&#13;
UM-30 ff. 4rv, 15r-16v, 18r-25v, 36rv: Life of Qirqos&#13;
UM-30 ff. 5r-7r: Homily of Theophilus, bishop of Aksum, on the wedding&#13;
at Cana&#13;
UM-30 ff. 7r-9v: Homily by Athanasius of Alexandria on the Incarnation&#13;
of the Word (in full)&#13;
UM-30 ff. 9v-12v: 53vr: Homily by Minas, bishop of Aksum, on the&#13;
Dormition of Mary&#13;
UM-30 ff. 13rv: Homily by Minas, bishop of Aksum, for the feast of the&#13;
70 disciples and the 318 Orthodox from Nicea&#13;
UM-30 f. 13v: Homily by Cyril of Alexandria for the feast of John the&#13;
Evangelist&#13;
UM-30 ff. 14rv: Homily by John Chrysostom on the Annunciation of Gabriel&#13;
to Mary, for the second Sunday of Taḫśaś&#13;
UM-30 ff. 17rv, 27rv: Life of George&#13;
FOLIATION SKIPS FROM 25 to 27&#13;
UM-30 ff. 28r-29v, 31rv, 35rv: Story of the appearance of the Cross to&#13;
Constantine&#13;
UM-30 ff. 30rv: Lives of Sergius and Bacchus&#13;
UM-30 ff. 32vr: Martyrdom of Aretha&#13;
UM-30 ff. 33rv: passage from Zechariah&#13;
UM-30 ff. 34vr: Homily of Jacob of Serug on the Nativity, to be read on&#13;
the commemoration of the holy innocents&#13;
UM-30 ff. 37rv: Homily on the great spiritual Easter&#13;
UM-30 ff. 38rv: Lament of Mary&#13;
UM-30 ff. 39rv: Homily on Mary for 3 Taḫśaś&#13;
UM-30 f. 40v: Homily for the third Saturday in Lent&#13;
UM-30 ff. 40vr: Homily by Jacob of Serug for the third Sunday in Lent&#13;
UM-30 ff. 41rv: Homily on the suffering of Jesus for Monday in&#13;
Easter-week&#13;
UM-30 ff. 42r-47r: Matthew 26:75-28:20&#13;
UM-30 ff. 47rv: Chapters for Mark, incomplete&#13;
UM-30 ff. 48rv: Matt 25:11-26&#13;
UM-30 ff. 49rv: Matt 24:[29]-42&#13;
UM-30 ff. 50rv: Matt 26:[17]-29&#13;
UM-30 ff. 51r-52v: Mark 1:1-[19] (both fragments belong to the same&#13;
leaf)&#13;
(Ted Erho, 28.06.2015)</shortcontent>
</shortcontents>
<subjects class="MCRMetaClassification" heritable="false" notinherit="false"><subject inherited="0" classid="domlib_class_00000002" categid="Sub02"/>
</subjects>
<restorations class="MCRMetaClassification" heritable="false" notinherit="false"><restoration inherited="0" classid="domlib_class_00000007" categid="Res03"/>
</restorations>
<desccontents class="DLMetaContent" heritable="false" notinherit="false"><desccontent xml:lang="en" inherited="0"><editions class="DLBibliography"><edition xml:lang="en" inherited="0"><isLink>no</isLink></edition></editions><literatures class="DLBibliography"><literature xml:lang="en" inherited="0"><isLink>no</isLink></literature></literatures></desccontent>
</desccontents>
</metadata><service><servdates class="MCRMetaISO8601Date"><servdate inherited="0" type="createdate">2015-07-17T16:01:39.937Z</servdate><servdate inherited="0" type="modifydate">2015-12-16T11:53:06.714Z</servdate></servdates><servflags class="MCRMetaLangText"><servflag xml:lang="en" inherited="0" form="plain" type="creator">DNosnitsin</servflag><servflag xml:lang="en" inherited="0" form="plain" type="editor">DNosnitsin</servflag></servflags><servacls class="MCRMetaAccessRule"><servacl permission="read"><condition format="xml"><boolean operator="true"/></condition></servacl><servacl permission="writedb"><condition format="xml"><boolean operator="and"><boolean operator="or"><condition field="group" operator="=" value="admingroup"/><condition field="group" operator="=" value="ethioleaders"/></boolean><boolean operator="true"/><boolean operator="true"/></boolean></condition></servacl><servacl permission="deletedb"><condition format="xml"><boolean operator="and"><boolean operator="or"><condition field="group" operator="=" value="admingroup"/><condition field="group" operator="=" value="ethioadmins"/></boolean><boolean operator="true"/><boolean operator="true"/></boolean></condition></servacl></servacls></service></mycoreobject>